ulidchemy/__init__.py
ulidchemy-0.1.0.dist-info/METADATA
ulidchemy-0.1.0.dist-info/WHEEL
ulidchemy-0.1.0.dist-info/RECORD
